tockloader/__init__.py
tockloader/_version.py
tockloader/app_installed.py
tockloader/app_padding.py
tockloader/app_tab.py
tockloader/board_interface.py
tockloader/bootloader_serial.py
tockloader/display.py
tockloader/exceptions.py
tockloader/flash_file.py
tockloader/helpers.py
tockloader/jlinkexe.py
tockloader/kernel_attributes.py
tockloader/main.py
tockloader/nrfjprog.py
tockloader/openocd.py
tockloader/probers.py
tockloader/stlink.py
tockloader/tab.py
tockloader/tbfh.py
tockloader/tickv.py
tockloader/tockloader.py
tockloader/static/bscan_spi_xc7a100t.bit
tockloader/static/bscan_spi_xc7a35t.bit
tockloader-1.16.0.dist-info/entry_points.txt
tockloader-1.16.0.dist-info/licenses/LICENSE
tockloader-1.16.0.dist-info/WHEEL
tockloader-1.16.0.dist-info/METADATA
tockloader-1.16.0.dist-info/RECORD
