Metadata-Version: 2.4
Name: tockloader
Version: 1.16.0
Summary: Tockloader is a tool for installing Tock applications.
Author-email: Tock Project Developers <devel@lists.tockos.org>
Requires-Python: >= 3.9
License-Expression: MIT
License-File: LICENSE
Requires-Dist: appdirs >= 1.4.4
Requires-Dist: argcomplete >= 1.8.2
Requires-Dist: colorama >= 0.3.7
Requires-Dist: crcmod >= 1.7
Requires-Dist: ecdsa >= 0.19.1
Requires-Dist: pycryptodome >= 3.15.0
Requires-Dist: pynrfjprog == 10.19.0
Requires-Dist: pyserial >= 3.0.1
Requires-Dist: siphash >= 0.0.1
Requires-Dist: six >= 1.9.0
Requires-Dist: toml >= 0.10.2
Requires-Dist: tqdm >= 4.45.0 
Requires-Dist: questionary >= 1.10.0
Project-URL: Home, https://github.com/tock/tockloader
